dotpyle/.dotpyle-complete.bash
dotpyle/.dotpyle-complete.fish
dotpyle/.dotpyle-complete.zsh
dotpyle/__init__.py
dotpyle/autocomplete-install.sh
dotpyle/commands/__init__.py
dotpyle/commands/add/__init__.py
dotpyle/commands/add/dotfile.py
dotpyle/commands/add/script.py
dotpyle/commands/commit.py
dotpyle/commands/config.py
dotpyle/commands/edit/__init__.py
dotpyle/commands/edit/config.py
dotpyle/commands/edit/dotfile.py
dotpyle/commands/edit/readme.py
dotpyle/commands/init.py
dotpyle/commands/link.py
dotpyle/commands/ls.py
dotpyle/commands/pull.py
dotpyle/commands/push.py
dotpyle/commands/run.py
dotpyle/commands/shell.py
dotpyle/commands/switch.py
dotpyle/commands/unlink.py
dotpyle/decorators/__init__.py
dotpyle/decorators/pass_config_handler.py
dotpyle/decorators/pass_config_manager.py
dotpyle/decorators/pass_file_handler.py
dotpyle/decorators/pass_local_handler.py
dotpyle/decorators/pass_logger.py
dotpyle/decorators/pass_repo_handler.py
dotpyle/errors/InvalidConfigFile.py
dotpyle/errors/__init__.py
dotpyle/exceptions.py
dotpyle/main.py
dotpyle/objects/__init__.py
dotpyle/objects/action.py
dotpyle/objects/base.py
dotpyle/objects/dotfile.py
dotpyle/objects/profile.py
dotpyle/objects/script.py
dotpyle/services/__init__.py
dotpyle/services/config_checker.py
dotpyle/services/config_handler.py
dotpyle/services/config_manager.py
dotpyle/services/file_handler.py
dotpyle/services/logger.py
dotpyle/services/repo_handler.py
dotpyle/templates/__init__.py
dotpyle/templates/basic-config.yaml
dotpyle/templates/gitignore
dotpyle/templates/local-config.yaml
dotpyle/templates/readme.md
dotpyle/templates/script.yaml
dotpyle/utils/__init__.py
dotpyle/utils/autocompletion.py
dotpyle/utils/constants.py
dotpyle/utils/path.py
dotpyle/utils/process.py
dotpyle/utils/schema.json
dotpyle/utils/url.py
dotpyle-0.1.4.dist-info/entry_points.txt
dotpyle-0.1.4.dist-info/LICENSE
dotpyle-0.1.4.dist-info/WHEEL
dotpyle-0.1.4.dist-info/METADATA
dotpyle-0.1.4.dist-info/RECORD
