Metadata-Version: 2.1
Name: dotpyle
Version: 0.1.4
Summary: Dotpyle is a Python implementation of a dotfile system manager, allowing users to keep a secure copy of all program configurations remotely, create different profiles, etc.
Home-page: https://github.com/jorgebodega/dotpyle
License: MIT
Author: Jorge Bodega
Author-email: jorge.bodega.f@gmail.com
Maintainer: Perseo Gutiérrez
Maintainer-email: perseo.gi98@gmail.com
Requires-Python: >=3.9,<4.0
Classifier: License :: OSI Approved :: MIT License
Classifier: Programming Language :: Python :: 3
Classifier: Programming Language :: Python :: 3.10
Classifier: Programming Language :: Python :: 3.9
Requires-Dist: Cerberus (>=1.3.2,<2.0.0)
Requires-Dist: GitPython (>=3.1.24,<4.0.0)
Requires-Dist: PyYAML (>=5.4.1,<6.0.0)
Requires-Dist: click (>=8.0.1,<9.0.0)
Requires-Dist: rich (>=10.1.0,<11.0.0)
Requires-Dist: setuptools (>=57.4.0,<58.0.0)
Project-URL: Repository, https://github.com/jorgebodega/dotpyle
